digdaglog2sql/__init__.py
digdaglog2sql/cli.py
digdaglog2sql/extractor.py
digdaglog2sql/td_op.py
digdaglog2sql-0.1.0.dist-info/LICENSE
digdaglog2sql-0.1.0.dist-info/METADATA
digdaglog2sql-0.1.0.dist-info/WHEEL
digdaglog2sql-0.1.0.dist-info/entry_points.txt
digdaglog2sql-0.1.0.dist-info/RECORD
