Metadata-Version: 2.1
Name: digdaglog2sql
Version: 0.1.0
Summary: Extract SQLs from digdag log
License: Apache-2.0
Author: Aki Ariga
Author-email: chezou@gmail.com
Maintainer: Aki Ariga
Maintainer-email: chezou@gmail.com
Requires-Python: >=3.8.1,<4.0.0
Classifier: License :: OSI Approved :: Apache Software License
Classifier: Programming Language :: Python :: 3
Classifier: Programming Language :: Python :: 3.9
Classifier: Programming Language :: Python :: 3.10
Classifier: Programming Language :: Python :: 3.11
Classifier: Programming Language :: Python :: 3.12
Requires-Dist: click (>=8.1.3,<9.0.0)
Requires-Dist: cloup (>=0.14.0,<0.15.0)
Requires-Dist: taskipy (>=1.10.1,<2.0.0)
Requires-Dist: tdworkflow (>=0.8.3,<0.9.0)
